neural_speed.libs/libgomp-a97153a2.so.1.0.0
neural_speed/run_bloom
neural_speed/run_polyglot
neural_speed/quant_falcon
neural_speed/quant_gptneox
neural_speed/quant_baichuan
neural_speed/quant_opt
neural_speed/run_whisper
neural_speed/quant_whisper
neural_speed/quant_mixtral
neural_speed/run_qwen
neural_speed/run_mixtral
neural_speed/gptneox_cpp.cpython-39-x86_64-linux-gnu.so
neural_speed/mistral_cpp.cpython-39-x86_64-linux-gnu.so
neural_speed/run_dolly
neural_speed/libne_layers.so
neural_speed/run_phi
neural_speed/gemma_cpp.cpython-39-x86_64-linux-gnu.so
neural_speed/quant_mpt
neural_speed/quant_phi
neural_speed/run_baichuan
neural_speed/run_llama
neural_speed/quant_chatglm2
neural_speed/run_falcon
neural_speed/opt_cpp.cpython-39-x86_64-linux-gnu.so
neural_speed/quant_gptj
neural_speed/baichuan_cpp.cpython-39-x86_64-linux-gnu.so
neural_speed/run_chatglm
neural_speed/quant_gemma
neural_speed/quant_chatglm
neural_speed/run_chatglm3
neural_speed/libGptjPyBind.so
neural_speed/quant_starcoder
neural_speed/starcoder_cpp.cpython-39-x86_64-linux-gnu.so
neural_speed/falcon_cpp.cpython-39-x86_64-linux-gnu.so
neural_speed/quant_stablelm
neural_speed/llama_cpp.cpython-39-x86_64-linux-gnu.so
neural_speed/run_gptneox
neural_speed/chatglm2_cpp.cpython-39-x86_64-linux-gnu.so
neural_speed/run_gemma
neural_speed/run_mistral
neural_speed/polyglot_cpp.cpython-39-x86_64-linux-gnu.so
neural_speed/quant_qwen
neural_speed/mpt_cpp.cpython-39-x86_64-linux-gnu.so
neural_speed/run_opt
neural_speed/whisper_cpp.cpython-39-x86_64-linux-gnu.so
neural_speed/bloom_cpp.cpython-39-x86_64-linux-gnu.so
neural_speed/quant_chatglm3
neural_speed/chatglm_cpp.cpython-39-x86_64-linux-gnu.so
neural_speed/quant_dolly
neural_speed/run_chatglm2
neural_speed/run_stablelm
neural_speed/stablelm_cpp.cpython-39-x86_64-linux-gnu.so
neural_speed/pybind_gptj
neural_speed/run_mpt
neural_speed/run_gptj
neural_speed/gptj_cpp.cpython-39-x86_64-linux-gnu.so
neural_speed-1.0.dist-info/top_level.txt
neural_speed-1.0.dist-info/LICENSE
neural_speed-1.0.dist-info/METADATA
neural_speed-1.0.dist-info/WHEEL
neural_speed-1.0.dist-info/RECORD
