Metadata-Version: 2.1
Name: neural-speed
Version: 1.0
Summary: Repository of Intel® Intel Extension for Transformers
Home-page: https://github.com/intel/neural-speed
Author: Intel AISE/AIPC Team
Author-email: feng.tian@intel.com, haihao.shen@intel.com,hanwen.chang@intel.com, penghui.cheng@intel.com
License: Apache 2.0
Keywords: Large Language Model,LLM,sub-byte
Classifier: Intended Audience :: Science/Research
Classifier: Programming Language :: Python :: 3
Classifier: Topic :: Scientific/Engineering :: Artificial Intelligence
Classifier: License :: OSI Approved :: Apache Software License
Requires-Python: >=3.7.0
License-File: LICENSE
